pybaidu/__init__.py
pybaidu/__main__.py
pybaidu/image.py
pybaidu/knew.py
pybaidu/library.py
pybaidu/locals.py
pybaidu/search.py
pybaidu/translate.py
pybaidu/video.py
pybaidu-1.0.0.dist-info/LICENSE
pybaidu-1.0.0.dist-info/METADATA
pybaidu-1.0.0.dist-info/WHEEL
pybaidu-1.0.0.dist-info/top_level.txt
pybaidu-1.0.0.dist-info/RECORD
