Metadata-Version: 2.1
Name: pybaidu
Version: 1.0.0
Summary: pybaidu是一个通过python爬虫请求百度来获取百度信息的python第三方库。
Home-page: https://gitcode.net/weixin_38805653/pybaidu
Author: stripe-python
Author-email: 13513519246@139.com
Maintainer: stripe-python
Maintainer-email: 13513519246@139.com
License: UNKNOWN
Download-URL: https://gitcode.net/weixin_38805653/pybaidu
Platform: UNKNOWN
Classifier: Programming Language :: Python :: 3
Classifier: License :: OSI Approved :: MIT License
Classifier: Operating System :: OS Independent
Requires-Python: >=3.6
Requires-Dist: requests
Requires-Dist: beautifulsoup4
Requires-Dist: python-pptx
Requires-Dist: PyExecJS
